{
    "29": {
        "StnPresMaxTime": "2018-12-29 08:06",
        "StnPres": "902.6",
        "RH": "99",
        "SeaPres": "...",
        "T Max Time": "2018-12-29 23:36",
        "UVI Max": "...",
        "Td dew point": "...",
        "T Min": "4.0",
        "Temperature": "5.0",
        "T Min Time": "2018-12-29 08:43",
        "GloblRad": "...",
        "ObsTime": "29",
        "Cloud Amount": "...",
        "RHMinTime": "2018-12-29 05:25",
        "WD": "72",
        "WDGust": "65",
        "PrecpHour": "...",
        "StnPresMin": "900.5",
        "RHMin": "98",
        "StnPresMinTime": "2018-12-29 13:21",
        "WGustTime": "2018-12-29 05:06",
        "WS": "6.6",
        "StnPresMax": "904.6",
        "VisbMean": "...",
        "SunShine": "...",
        "PrecpMax10": "...",
        "PrecpMax10Time": "",
        "EvapA": "...",
        "T Max": "6.4",
        "UVI Max Time": "",
        "PrecpHrMax": "...",
        "WSGust": "23.7",
        "PrecpHrMaxTime": "",
        "SunShineRate": "...",
        "Precp": "21.0"
    },
    "27": {
        "StnPresMaxTime": "2018-12-27 23:03",
        "StnPres": "895.6",
        "RH": "99",
        "SeaPres": "...",
        "T Max Time": "2018-12-27 00:01",
        "UVI Max": "...",
        "Td dew point": "...",
        "T Min": "7.3",
        "Temperature": "9.9",
        "T Min Time": "2018-12-27 23:34",
        "GloblRad": "...",
        "ObsTime": "27",
        "Cloud Amount": "...",
        "RHMinTime": "2018-12-27 08:53",
        "WD": "64",
        "WDGust": "69",
        "PrecpHour": "...",
        "StnPresMin": "894.0",
        "RHMin": "98",
        "StnPresMinTime": "2018-12-27 00:33",
        "WGustTime": "2018-12-27 19:49",
        "WS": "8.6",
        "StnPresMax": "898.4",
        "VisbMean": "...",
        "SunShine": "...",
        "PrecpMax10": "...",
        "PrecpMax10Time": "",
        "EvapA": "...",
        "T Max": "12.7",
        "UVI Max Time": "",
        "PrecpHrMax": "...",
        "WSGust": "24.2",
        "PrecpHrMaxTime": "",
        "SunShineRate": "...",
        "Precp": "30.5"
    },
    "04": {
        "StnPresMaxTime": "2018-12-04 09:11",
        "StnPres": "898.1",
        "RH": "86",
        "SeaPres": "...",
        "T Max Time": "2018-12-04 12:42",
        "UVI Max": "...",
        "Td dew point": "...",
        "T Min": "14.1",
        "Temperature": "18.0",
        "T Min Time": "2018-12-04 23:51",
        "GloblRad": "...",
        "ObsTime": "04",
        "Cloud Amount": "...",
        "RHMinTime": "2018-12-04 00:01",
        "WD": "269",
        "WDGust": "70",
        "PrecpHour": "...",
        "StnPresMin": "896.9",
        "RHMin": "46",
        "StnPresMinTime": "2018-12-04 03:41",
        "WGustTime": "2018-12-04 23:42",
        "WS": "3.4",
        "StnPresMax": "899.8",
        "VisbMean": "...",
        "SunShine": "...",
        "PrecpMax10": "...",
        "PrecpMax10Time": "",
        "EvapA": "...",
        "T Max": "23.2",
        "UVI Max Time": "",
        "PrecpHrMax": "...",
        "WSGust": "9.9",
        "PrecpHrMaxTime": "",
        "SunShineRate": "...",
        "Precp": "0.5"
    },
    "20": {
        "StnPresMaxTime": "2018-12-20 09:21",
        "StnPres": "896.6",
        "RH": "56",
        "SeaPres": "...",
        "T Max Time": "2018-12-20 13:26",
        "UVI Max": "...",
        "Td dew point": "...",
        "T Min": "11.3",
        "Temperature": "15.6",
        "T Min Time": "2018-12-20 01:21",
        "GloblRad": "...",
        "ObsTime": "20",
        "Cloud Amount": "...",
        "RHMinTime": "2018-12-20 02:31",
        "WD": "121",
        "WDGust": "249",
        "PrecpHour": "...",
        "StnPresMin": "895.0",
        "RHMin": "17",
        "StnPresMinTime": "2018-12-20 14:41",
        "WGustTime": "2018-12-20 02:57",
        "WS": "4.5",
        "StnPresMax": "898.1",
        "VisbMean": "...",
        "SunShine": "...",
        "PrecpMax10": "...",
        "PrecpMax10Time": "",
        "EvapA": "...",
        "T Max": "21.5",
        "UVI Max Time": "",
        "PrecpHrMax": "...",
        "WSGust": "13.2",
        "PrecpHrMaxTime": "",
        "SunShineRate": "...",
        "Precp": "0.0"
    },
    "07": {
        "StnPresMaxTime": "2018-12-07 22:51",
        "StnPres": "898.8",
        "RH": "99",
        "SeaPres": "...",
        "T Max Time": "2018-12-07 00:02",
        "UVI Max": "...",
        "Td dew point": "...",
        "T Min": "10.5",
        "Temperature": "11.3",
        "T Min Time": "2018-12-07 10:21",
        "GloblRad": "...",
        "ObsTime": "07",
        "Cloud Amount": "...",
        "RHMinTime": "2018-12-07 09:25",
        "WD": "72",
        "WDGust": "47",
        "PrecpHour": "...",
        "StnPresMin": "896.8",
        "RHMin": "99",
        "StnPresMinTime": "2018-12-07 14:52",
        "WGustTime": "2018-12-07 08:27",
        "WS": "4.0",
        "StnPresMax": "901.1",
        "VisbMean": "...",
        "SunShine": "...",
        "PrecpMax10": "...",
        "PrecpMax10Time": "",
        "EvapA": "...",
        "T Max": "14.0",
        "UVI Max Time": "",
        "PrecpHrMax": "...",
        "WSGust": "19.8",
        "PrecpHrMaxTime": "",
        "SunShineRate": "...",
        "Precp": "17.5"
    },
    "31": {
        "StnPresMaxTime": "2018-12-31 09:52",
        "StnPres": "902.5",
        "RH": "99",
        "SeaPres": "...",
        "T Max Time": "2018-12-31 11:11",
        "UVI Max": "...",
        "Td dew point": "...",
        "T Min": "6.7",
        "Temperature": "9.4",
        "T Min Time": "2018-12-31 16:41",
        "GloblRad": "...",
        "ObsTime": "31",
        "Cloud Amount": "...",
        "RHMinTime": "2018-12-31 01:41",
        "WD": "76",
        "WDGust": "121",
        "PrecpHour": "...",
        "StnPresMin": "897.8",
        "RHMin": "96",
        "StnPresMinTime": "2018-12-31 14:11",
        "WGustTime": "2018-12-31 14:19",
        "WS": "4.2",
        "StnPresMax": "904.7",
        "VisbMean": "...",
        "SunShine": "...",
        "PrecpMax10": "...",
        "PrecpMax10Time": "",
        "EvapA": "...",
        "T Max": "10.3",
        "UVI Max Time": "",
        "PrecpHrMax": "...",
        "WSGust": "20.4",
        "PrecpHrMaxTime": "",
        "SunShineRate": "...",
        "Precp": "24.5"
    },
    "06": {
        "StnPresMaxTime": "2018-12-06 09:55",
        "StnPres": "896.9",
        "RH": "93",
        "SeaPres": "...",
        "T Max Time": "2018-12-06 14:17",
        "UVI Max": "...",
        "Td dew point": "...",
        "T Min": "13.9",
        "Temperature": "17.3",
        "T Min Time": "2018-12-06 20:31",
        "GloblRad": "...",
        "ObsTime": "06",
        "Cloud Amount": "...",
        "RHMinTime": "2018-12-06 14:23",
        "WD": "70",
        "WDGust": "56",
        "PrecpHour": "...",
        "StnPresMin": "895.7",
        "RHMin": "73",
        "StnPresMinTime": "2018-12-06 02:32",
        "WGustTime": "2018-12-06 22:02",
        "WS": "2.6",
        "StnPresMax": "898.5",
        "VisbMean": "...",
        "SunShine": "...",
        "PrecpMax10": "...",
        "PrecpMax10Time": "",
        "EvapA": "...",
        "T Max": "22.4",
        "UVI Max Time": "",
        "PrecpHrMax": "...",
        "WSGust": "11.5",
        "PrecpHrMaxTime": "",
        "SunShineRate": "...",
        "Precp": "1.0"
    },
    "25": {
        "StnPresMaxTime": "2018-12-25 08:51",
        "StnPres": "894.5",
        "RH": "99",
        "SeaPres": "...",
        "T Max Time": "2018-12-25 15:03",
        "UVI Max": "...",
        "Td dew point": "...",
        "T Min": "12.2",
        "Temperature": "14.9",
        "T Min Time": "2018-12-25 00:08",
        "GloblRad": "...",
        "ObsTime": "25",
        "Cloud Amount": "...",
        "RHMinTime": "2018-12-25 23:42",
        "WD": "115",
        "WDGust": "118",
        "PrecpHour": "...",
        "StnPresMin": "893.1",
        "RHMin": "98",
        "StnPresMinTime": "2018-12-25 13:17",
        "WGustTime": "2018-12-25 02:54",
        "WS": "3.4",
        "StnPresMax": "896.7",
        "VisbMean": "...",
        "SunShine": "...",
        "PrecpMax10": "...",
        "PrecpMax10Time": "",
        "EvapA": "...",
        "T Max": "16.6",
        "UVI Max Time": "",
        "PrecpHrMax": "...",
        "WSGust": "11.0",
        "PrecpHrMaxTime": "",
        "SunShineRate": "...",
        "Precp": "5.0"
    },
    "09": {
        "StnPresMaxTime": "2018-12-09 09:48",
        "StnPres": "899.1",
        "RH": "99",
        "SeaPres": "...",
        "T Max Time": "2018-12-09 23:54",
        "UVI Max": "...",
        "Td dew point": "...",
        "T Min": "10.0",
        "Temperature": "11.3",
        "T Min Time": "2018-12-09 07:53",
        "GloblRad": "...",
        "ObsTime": "09",
        "Cloud Amount": "...",
        "RHMinTime": "2018-12-09 23:43",
        "WD": "227",
        "WDGust": "41",
        "PrecpHour": "...",
        "StnPresMin": "897.0",
        "RHMin": "99",
        "StnPresMinTime": "2018-12-09 16:21",
        "WGustTime": "2018-12-09 14:14",
        "WS": "3.9",
        "StnPresMax": "901.8",
        "VisbMean": "...",
        "SunShine": "...",
        "PrecpMax10": "...",
        "PrecpMax10Time": "",
        "EvapA": "...",
        "T Max": "13.0",
        "UVI Max Time": "",
        "PrecpHrMax": "...",
        "WSGust": "17.6",
        "PrecpHrMaxTime": "",
        "SunShineRate": "...",
        "Precp": "18.0"
    },
    "12": {
        "StnPresMaxTime": "2018-12-12 08:33",
        "StnPres": "901.2",
        "RH": "99",
        "SeaPres": "...",
        "T Max Time": "2018-12-12 00:01",
        "UVI Max": "...",
        "Td dew point": "...",
        "T Min": "7.0",
        "Temperature": "7.9",
        "T Min Time": "2018-12-12 17:31",
        "GloblRad": "...",
        "ObsTime": "12",
        "Cloud Amount": "...",
        "RHMinTime": "2018-12-12 16:13",
        "WD": "66",
        "WDGust": "63",
        "PrecpHour": "...",
        "StnPresMin": "899.5",
        "RHMin": "99",
        "StnPresMinTime": "2018-12-12 00:21",
        "WGustTime": "2018-12-12 00:17",
        "WS": "5.3",
        "StnPresMax": "903.3",
        "VisbMean": "...",
        "SunShine": "...",
        "PrecpMax10": "...",
        "PrecpMax10Time": "",
        "EvapA": "...",
        "T Max": "9.2",
        "UVI Max Time": "",
        "PrecpHrMax": "...",
        "WSGust": "19.3",
        "PrecpHrMaxTime": "",
        "SunShineRate": "...",
        "Precp": "8.0"
    },
    "02": {
        "StnPresMaxTime": "2018-12-02 09:41",
        "StnPres": "897.1",
        "RH": "71",
        "SeaPres": "...",
        "T Max Time": "2018-12-02 14:42",
        "UVI Max": "...",
        "Td dew point": "...",
        "T Min": "13.7",
        "Temperature": "17.5",
        "T Min Time": "2018-12-02 00:41",
        "GloblRad": "...",
        "ObsTime": "02",
        "Cloud Amount": "...",
        "RHMinTime": "2018-12-02 23:01",
        "WD": "114",
        "WDGust": "112",
        "PrecpHour": "...",
        "StnPresMin": "895.5",
        "RHMin": "30",
        "StnPresMinTime": "2018-12-02 13:34",
        "WGustTime": "2018-12-02 04:07",
        "WS": "2.7",
        "StnPresMax": "898.5",
        "VisbMean": "...",
        "SunShine": "...",
        "PrecpMax10": "...",
        "PrecpMax10Time": "",
        "EvapA": "...",
        "T Max": "21.3",
        "UVI Max Time": "",
        "PrecpHrMax": "...",
        "WSGust": "12.1",
        "PrecpHrMaxTime": "",
        "SunShineRate": "...",
        "Precp": "0.0"
    },
    "28": {
        "StnPresMaxTime": "2018-12-28 21:38",
        "StnPres": "899.8",
        "RH": "99",
        "SeaPres": "...",
        "T Max Time": "2018-12-28 11:42",
        "UVI Max": "...",
        "Td dew point": "...",
        "T Min": "4.9",
        "Temperature": "6.7",
        "T Min Time": "2018-12-28 23:41",
        "GloblRad": "...",
        "ObsTime": "28",
        "Cloud Amount": "...",
        "RHMinTime": "2018-12-28 11:19",
        "WD": "71",
        "WDGust": "63",
        "PrecpHour": "...",
        "StnPresMin": "896.7",
        "RHMin": "98",
        "StnPresMinTime": "2018-12-28 02:02",
        "WGustTime": "2018-12-28 15:01",
        "WS": "8.6",
        "StnPresMax": "902.2",
        "VisbMean": "...",
        "SunShine": "...",
        "PrecpMax10": "...",
        "PrecpMax10Time": "",
        "EvapA": "...",
        "T Max": "7.7",
        "UVI Max Time": "",
        "PrecpHrMax": "...",
        "WSGust": "24.8",
        "PrecpHrMaxTime": "",
        "SunShineRate": "...",
        "Precp": "32.0"
    },
    "08": {
        "StnPresMaxTime": "2018-12-08 09:41",
        "StnPres": "899.7",
        "RH": "99",
        "SeaPres": "...",
        "T Max Time": "2018-12-08 11:45",
        "UVI Max": "...",
        "Td dew point": "...",
        "T Min": "9.7",
        "Temperature": "10.8",
        "T Min Time": "2018-12-08 06:42",
        "GloblRad": "...",
        "ObsTime": "08",
        "Cloud Amount": "...",
        "RHMinTime": "2018-12-08 09:03",
        "WD": "71",
        "WDGust": "71",
        "PrecpHour": "...",
        "StnPresMin": "898.3",
        "RHMin": "99",
        "StnPresMinTime": "2018-12-08 17:43",
        "WGustTime": "2018-12-08 21:35",
        "WS": "3.9",
        "StnPresMax": "902.0",
        "VisbMean": "...",
        "SunShine": "...",
        "PrecpMax10": "...",
        "PrecpMax10Time": "",
        "EvapA": "...",
        "T Max": "11.9",
        "UVI Max Time": "",
        "PrecpHrMax": "...",
        "WSGust": "19.3",
        "PrecpHrMaxTime": "",
        "SunShineRate": "...",
        "Precp": "19.0"
    },
    "17": {
        "StnPresMaxTime": "2018-12-17 10:04",
        "StnPres": "899.4",
        "RH": "87",
        "SeaPres": "...",
        "T Max Time": "2018-12-17 13:11",
        "UVI Max": "...",
        "Td dew point": "...",
        "T Min": "4.5",
        "Temperature": "6.5",
        "T Min Time": "2018-12-17 07:01",
        "GloblRad": "...",
        "ObsTime": "17",
        "Cloud Amount": "...",
        "RHMinTime": "2018-12-17 15:11",
        "WD": "66",
        "WDGust": "55",
        "PrecpHour": "...",
        "StnPresMin": "897.5",
        "RHMin": "32",
        "StnPresMinTime": "2018-12-17 02:31",
        "WGustTime": "2018-12-17 19:40",
        "WS": "5.3",
        "StnPresMax": "901.4",
        "VisbMean": "...",
        "SunShine": "...",
        "PrecpMax10": "...",
        "PrecpMax10Time": "",
        "EvapA": "...",
        "T Max": "9.8",
        "UVI Max Time": "",
        "PrecpHrMax": "...",
        "WSGust": "18.2",
        "PrecpHrMaxTime": "",
        "SunShineRate": "...",
        "Precp": "1.0"
    },
    "16": {
        "StnPresMaxTime": "2018-12-16 09:51",
        "StnPres": "899.3",
        "RH": "98",
        "SeaPres": "...",
        "T Max Time": "2018-12-16 10:21",
        "UVI Max": "...",
        "Td dew point": "...",
        "T Min": "8.1",
        "Temperature": "12.8",
        "T Min Time": "2018-12-16 23:57",
        "GloblRad": "...",
        "ObsTime": "16",
        "Cloud Amount": "...",
        "RHMinTime": "2018-12-16 10:34",
        "WD": "321",
        "WDGust": "27",
        "PrecpHour": "...",
        "StnPresMin": "897.7",
        "RHMin": "75",
        "StnPresMinTime": "2018-12-16 14:51",
        "WGustTime": "2018-12-16 23:33",
        "WS": "3.4",
        "StnPresMax": "901.7",
        "VisbMean": "...",
        "SunShine": "...",
        "PrecpMax10": "...",
        "PrecpMax10Time": "",
        "EvapA": "...",
        "T Max": "17.9",
        "UVI Max Time": "",
        "PrecpHrMax": "...",
        "WSGust": "9.3",
        "PrecpHrMaxTime": "",
        "SunShineRate": "...",
        "Precp": "0.0"
    },
    "14": {
        "StnPresMaxTime": "2018-12-14 08:31",
        "StnPres": "901.8",
        "RH": "99",
        "SeaPres": "...",
        "T Max Time": "2018-12-14 12:31",
        "UVI Max": "...",
        "Td dew point": "...",
        "T Min": "9.9",
        "Temperature": "10.4",
        "T Min Time": "2018-12-14 00:01",
        "GloblRad": "...",
        "ObsTime": "14",
        "Cloud Amount": "...",
        "RHMinTime": "2018-12-14 22:17",
        "WD": "52",
        "WDGust": "53",
        "PrecpHour": "...",
        "StnPresMin": "900.5",
        "RHMin": "98",
        "StnPresMinTime": "2018-12-14 02:07",
        "WGustTime": "2018-12-14 23:00",
        "WS": "4.7",
        "StnPresMax": "903.4",
        "VisbMean": "...",
        "SunShine": "...",
        "PrecpMax10": "...",
        "PrecpMax10Time": "",
        "EvapA": "...",
        "T Max": "11.4",
        "UVI Max Time": "",
        "PrecpHrMax": "...",
        "WSGust": "20.9",
        "PrecpHrMaxTime": "",
        "SunShineRate": "...",
        "Precp": "16.0"
    },
    "19": {
        "StnPresMaxTime": "2018-12-19 08:41",
        "StnPres": "898.3",
        "RH": "75",
        "SeaPres": "...",
        "T Max Time": "2018-12-19 13:51",
        "UVI Max": "...",
        "Td dew point": "...",
        "T Min": "7.9",
        "Temperature": "12.4",
        "T Min Time": "2018-12-19 00:05",
        "GloblRad": "...",
        "ObsTime": "19",
        "Cloud Amount": "...",
        "RHMinTime": "2018-12-19 22:02",
        "WD": "107",
        "WDGust": "102",
        "PrecpHour": "...",
        "StnPresMin": "896.6",
        "RHMin": "43",
        "StnPresMinTime": "2018-12-19 15:03",
        "WGustTime": "2018-12-19 00:28",
        "WS": "3.1",
        "StnPresMax": "900.5",
        "VisbMean": "...",
        "SunShine": "...",
        "PrecpMax10": "...",
        "PrecpMax10Time": "",
        "EvapA": "...",
        "T Max": "18.7",
        "UVI Max Time": "",
        "PrecpHrMax": "...",
        "WSGust": "13.2",
        "PrecpHrMaxTime": "",
        "SunShineRate": "...",
        "Precp": "0.0"
    },
    "23": {
        "StnPresMaxTime": "2018-12-23 09:03",
        "StnPres": "897.3",
        "RH": "98",
        "SeaPres": "...",
        "T Max Time": "2018-12-23 00:12",
        "UVI Max": "...",
        "Td dew point": "...",
        "T Min": "10.5",
        "Temperature": "13.8",
        "T Min Time": "2018-12-23 23:15",
        "GloblRad": "...",
        "ObsTime": "23",
        "Cloud Amount": "...",
        "RHMinTime": "2018-12-23 00:12",
        "WD": "71",
        "WDGust": "52",
        "PrecpHour": "...",
        "StnPresMin": "895.0",
        "RHMin": "61",
        "StnPresMinTime": "2018-12-23 14:13",
        "WGustTime": "2018-12-23 15:40",
        "WS": "4.2",
        "StnPresMax": "898.9",
        "VisbMean": "...",
        "SunShine": "...",
        "PrecpMax10": "...",
        "PrecpMax10Time": "",
        "EvapA": "...",
        "T Max": "18.5",
        "UVI Max Time": "",
        "PrecpHrMax": "...",
        "WSGust": "23.1",
        "PrecpHrMaxTime": "",
        "SunShineRate": "...",
        "Precp": "33.0"
    },
    "03": {
        "StnPresMaxTime": "2018-12-03 09:01",
        "StnPres": "897.8",
        "RH": "48",
        "SeaPres": "...",
        "T Max Time": "2018-12-03 10:42",
        "UVI Max": "...",
        "Td dew point": "...",
        "T Min": "16.8",
        "Temperature": "19.3",
        "T Min Time": "2018-12-03 04:31",
        "GloblRad": "...",
        "ObsTime": "03",
        "Cloud Amount": "...",
        "RHMinTime": "2018-12-03 02:01",
        "WD": "283",
        "WDGust": "279",
        "PrecpHour": "...",
        "StnPresMin": "896.6",
        "RHMin": "14",
        "StnPresMinTime": "2018-12-03 14:11",
        "WGustTime": "2018-12-03 01:26",
        "WS": "2.6",
        "StnPresMax": "899.8",
        "VisbMean": "...",
        "SunShine": "...",
        "PrecpMax10": "...",
        "PrecpMax10Time": "",
        "EvapA": "...",
        "T Max": "24.6",
        "UVI Max Time": "",
        "PrecpHrMax": "...",
        "WSGust": "6.6",
        "PrecpHrMaxTime": "",
        "SunShineRate": "...",
        "Precp": "0.0"
    },
    "22": {
        "StnPresMaxTime": "2018-12-22 09:31",
        "StnPres": "897.6",
        "RH": "85",
        "SeaPres": "...",
        "T Max Time": "2018-12-22 12:41",
        "UVI Max": "...",
        "Td dew point": "...",
        "T Min": "14.1",
        "Temperature": "17.7",
        "T Min Time": "2018-12-22 03:41",
        "GloblRad": "...",
        "ObsTime": "22",
        "Cloud Amount": "...",
        "RHMinTime": "2018-12-22 20:41",
        "WD": "9",
        "WDGust": "143",
        "PrecpHour": "...",
        "StnPresMin": "896.3",
        "RHMin": "55",
        "StnPresMinTime": "2018-12-22 14:45",
        "WGustTime": "2018-12-22 00:36",
        "WS": "2.1",
        "StnPresMax": "899.2",
        "VisbMean": "...",
        "SunShine": "...",
        "PrecpMax10": "...",
        "PrecpMax10Time": "",
        "EvapA": "...",
        "T Max": "23.3",
        "UVI Max Time": "",
        "PrecpHrMax": "...",
        "WSGust": "11.0",
        "PrecpHrMaxTime": "",
        "SunShineRate": "...",
        "Precp": "0.0"
    },
    "21": {
        "StnPresMaxTime": "2018-12-21 08:32",
        "StnPres": "896.6",
        "RH": "92",
        "SeaPres": "...",
        "T Max Time": "2018-12-21 10:52",
        "UVI Max": "...",
        "Td dew point": "...",
        "T Min": "12.6",
        "Temperature": "14.6",
        "T Min Time": "2018-12-21 05:13",
        "GloblRad": "...",
        "ObsTime": "21",
        "Cloud Amount": "...",
        "RHMinTime": "2018-12-21 01:51",
        "WD": "88",
        "WDGust": "116",
        "PrecpHour": "...",
        "StnPresMin": "895.2",
        "RHMin": "52",
        "StnPresMinTime": "2018-12-21 15:51",
        "WGustTime": "2018-12-21 22:01",
        "WS": "3.0",
        "StnPresMax": "898.5",
        "VisbMean": "...",
        "SunShine": "...",
        "PrecpMax10": "...",
        "PrecpMax10Time": "",
        "EvapA": "...",
        "T Max": "17.9",
        "UVI Max Time": "",
        "PrecpHrMax": "...",
        "WSGust": "13.7",
        "PrecpHrMaxTime": "",
        "SunShineRate": "...",
        "Precp": "0.0"
    },
    "15": {
        "StnPresMaxTime": "2018-12-15 07:44",
        "StnPres": "900.6",
        "RH": "98",
        "SeaPres": "...",
        "T Max Time": "2018-12-15 23:41",
        "UVI Max": "...",
        "Td dew point": "...",
        "T Min": "10.2",
        "Temperature": "11.8",
        "T Min Time": "2018-12-15 01:04",
        "GloblRad": "...",
        "ObsTime": "15",
        "Cloud Amount": "...",
        "RHMinTime": "2018-12-15 03:06",
        "WD": "13",
        "WDGust": "66",
        "PrecpHour": "...",
        "StnPresMin": "898.8",
        "RHMin": "98",
        "StnPresMinTime": "2018-12-15 15:14",
        "WGustTime": "2018-12-15 06:40",
        "WS": "3.7",
        "StnPresMax": "902.3",
        "VisbMean": "...",
        "SunShine": "...",
        "PrecpMax10": "...",
        "PrecpMax10Time": "",
        "EvapA": "...",
        "T Max": "13.5",
        "UVI Max Time": "",
        "PrecpHrMax": "...",
        "WSGust": "19.3",
        "PrecpHrMaxTime": "",
        "SunShineRate": "...",
        "Precp": "7.5"
    },
    "18": {
        "StnPresMaxTime": "2018-12-18 10:13",
        "StnPres": "899.7",
        "RH": "82",
        "SeaPres": "...",
        "T Max Time": "2018-12-18 14:22",
        "UVI Max": "...",
        "Td dew point": "...",
        "T Min": "4.7",
        "Temperature": "8.1",
        "T Min Time": "2018-12-18 04:35",
        "GloblRad": "...",
        "ObsTime": "18",
        "Cloud Amount": "...",
        "RHMinTime": "2018-12-18 16:23",
        "WD": "61",
        "WDGust": "55",
        "PrecpHour": "...",
        "StnPresMin": "898.5",
        "RHMin": "13",
        "StnPresMinTime": "2018-12-18 13:31",
        "WGustTime": "2018-12-18 10:46",
        "WS": "3.2",
        "StnPresMax": "901.6",
        "VisbMean": "...",
        "SunShine": "...",
        "PrecpMax10": "...",
        "PrecpMax10Time": "",
        "EvapA": "...",
        "T Max": "13.9",
        "UVI Max Time": "",
        "PrecpHrMax": "...",
        "WSGust": "13.7",
        "PrecpHrMaxTime": "",
        "SunShineRate": "...",
        "Precp": "0.0"
    },
    "05": {
        "StnPresMaxTime": "2018-12-05 08:44",
        "StnPres": "897.2",
        "RH": "98",
        "SeaPres": "...",
        "T Max Time": "2018-12-05 23:51",
        "UVI Max": "...",
        "Td dew point": "...",
        "T Min": "12.7",
        "Temperature": "14.1",
        "T Min Time": "2018-12-05 01:33",
        "GloblRad": "...",
        "ObsTime": "05",
        "Cloud Amount": "...",
        "RHMinTime": "2018-12-05 04:32",
        "WD": "30",
        "WDGust": "119",
        "PrecpHour": "...",
        "StnPresMin": "895.2",
        "RHMin": "96",
        "StnPresMinTime": "2018-12-05 15:22",
        "WGustTime": "2018-12-05 16:32",
        "WS": "3.2",
        "StnPresMax": "899.5",
        "VisbMean": "...",
        "SunShine": "...",
        "PrecpMax10": "...",
        "PrecpMax10Time": "",
        "EvapA": "...",
        "T Max": "16.1",
        "UVI Max Time": "",
        "PrecpHrMax": "...",
        "WSGust": "13.7",
        "PrecpHrMaxTime": "",
        "SunShineRate": "...",
        "Precp": "4.0"
    },
    "10": {
        "StnPresMaxTime": "2018-12-10 10:01",
        "StnPres": "897.7",
        "RH": "99",
        "SeaPres": "...",
        "T Max Time": "2018-12-10 11:12",
        "UVI Max": "...",
        "Td dew point": "...",
        "T Min": "12.9",
        "Temperature": "15.0",
        "T Min Time": "2018-12-10 00:01",
        "GloblRad": "...",
        "ObsTime": "10",
        "Cloud Amount": "...",
        "RHMinTime": "2018-12-10 13:31",
        "WD": "242",
        "WDGust": "38",
        "PrecpHour": "...",
        "StnPresMin": "895.7",
        "RHMin": "99",
        "StnPresMinTime": "2018-12-10 15:32",
        "WGustTime": "2018-12-10 02:18",
        "WS": "2.2",
        "StnPresMax": "900.0",
        "VisbMean": "...",
        "SunShine": "...",
        "PrecpMax10": "...",
        "PrecpMax10Time": "",
        "EvapA": "...",
        "T Max": "16.1",
        "UVI Max Time": "",
        "PrecpHrMax": "...",
        "WSGust": "14.3",
        "PrecpHrMaxTime": "",
        "SunShineRate": "...",
        "Precp": "6.5"
    },
    "13": {
        "StnPresMaxTime": "2018-12-13 08:51",
        "StnPres": "901.2",
        "RH": "99",
        "SeaPres": "...",
        "T Max Time": "2018-12-13 10:03",
        "UVI Max": "...",
        "Td dew point": "...",
        "T Min": "8.1",
        "Temperature": "9.8",
        "T Min Time": "2018-12-13 00:01",
        "GloblRad": "...",
        "ObsTime": "13",
        "Cloud Amount": "...",
        "RHMinTime": "2018-12-13 10:41",
        "WD": "44",
        "WDGust": "39",
        "PrecpHour": "...",
        "StnPresMin": "899.6",
        "RHMin": "99",
        "StnPresMinTime": "2018-12-13 13:56",
        "WGustTime": "2018-12-13 19:28",
        "WS": "3.1",
        "StnPresMax": "902.9",
        "VisbMean": "...",
        "SunShine": "...",
        "PrecpMax10": "...",
        "PrecpMax10Time": "",
        "EvapA": "...",
        "T Max": "10.7",
        "UVI Max Time": "",
        "PrecpHrMax": "...",
        "WSGust": "16.0",
        "PrecpHrMaxTime": "",
        "SunShineRate": "...",
        "Precp": "9.0"
    },
    "11": {
        "StnPresMaxTime": "2018-12-11 22:55",
        "StnPres": "898.0",
        "RH": "99",
        "SeaPres": "...",
        "T Max Time": "2018-12-11 01:21",
        "UVI Max": "...",
        "Td dew point": "...",
        "T Min": "9.0",
        "Temperature": "13.3",
        "T Min Time": "2018-12-11 23:42",
        "GloblRad": "...",
        "ObsTime": "11",
        "Cloud Amount": "...",
        "RHMinTime": "2018-12-11 16:01",
        "WD": "64",
        "WDGust": "57",
        "PrecpHour": "...",
        "StnPresMin": "896.3",
        "RHMin": "98",
        "StnPresMinTime": "2018-12-11 00:33",
        "WGustTime": "2018-12-11 18:30",
        "WS": "5.0",
        "StnPresMax": "900.2",
        "VisbMean": "...",
        "SunShine": "...",
        "PrecpMax10": "...",
        "PrecpMax10Time": "",
        "EvapA": "...",
        "T Max": "16.1",
        "UVI Max Time": "",
        "PrecpHrMax": "...",
        "WSGust": "18.7",
        "PrecpHrMaxTime": "",
        "SunShineRate": "...",
        "Precp": "4.0"
    },
    "01": {
        "StnPresMaxTime": "2018-12-01 08:41",
        "StnPres": "898.5",
        "RH": "87",
        "SeaPres": "...",
        "T Max Time": "2018-12-01 11:32",
        "UVI Max": "...",
        "Td dew point": "...",
        "T Min": "13.6",
        "Temperature": "15.9",
        "T Min Time": "2018-12-01 00:43",
        "GloblRad": "...",
        "ObsTime": "01",
        "Cloud Amount": "...",
        "RHMinTime": "2018-12-01 08:51",
        "WD": "94",
        "WDGust": "104",
        "PrecpHour": "...",
        "StnPresMin": "897.2",
        "RHMin": "54",
        "StnPresMinTime": "2018-12-01 13:51",
        "WGustTime": "2018-12-01 21:23",
        "WS": "2.6",
        "StnPresMax": "900.5",
        "VisbMean": "...",
        "SunShine": "...",
        "PrecpMax10": "...",
        "PrecpMax10Time": "",
        "EvapA": "...",
        "T Max": "21.7",
        "UVI Max Time": "",
        "PrecpHrMax": "...",
        "WSGust": "10.4",
        "PrecpHrMaxTime": "",
        "SunShineRate": "...",
        "Precp": "0.0"
    },
    "26": {
        "StnPresMaxTime": "2018-12-26 08:51",
        "StnPres": "893.7",
        "RH": "99",
        "SeaPres": "...",
        "T Max Time": "2018-12-26 02:44",
        "UVI Max": "...",
        "Td dew point": "...",
        "T Min": "12.7",
        "Temperature": "14.6",
        "T Min Time": "2018-12-26 23:53",
        "GloblRad": "...",
        "ObsTime": "26",
        "Cloud Amount": "...",
        "RHMinTime": "2018-12-26 13:21",
        "WD": "64",
        "WDGust": "48",
        "PrecpHour": "...",
        "StnPresMin": "891.8",
        "RHMin": "98",
        "StnPresMinTime": "2018-12-26 12:53",
        "WGustTime": "2018-12-26 23:53",
        "WS": "3.4",
        "StnPresMax": "895.1",
        "VisbMean": "...",
        "SunShine": "...",
        "PrecpMax10": "...",
        "PrecpMax10Time": "",
        "EvapA": "...",
        "T Max": "16.5",
        "UVI Max Time": "",
        "PrecpHrMax": "...",
        "WSGust": "12.6",
        "PrecpHrMaxTime": "",
        "SunShineRate": "...",
        "Precp": "2.0"
    },
    "30": {
        "StnPresMaxTime": "2018-12-30 09:23",
        "StnPres": "901.4",
        "RH": "99",
        "SeaPres": "...",
        "T Max Time": "2018-12-30 23:53",
        "UVI Max": "...",
        "Td dew point": "...",
        "T Min": "5.9",
        "Temperature": "7.7",
        "T Min Time": "2018-12-30 00:42",
        "GloblRad": "...",
        "ObsTime": "30",
        "Cloud Amount": "...",
        "RHMinTime": "2018-12-30 13:41",
        "WD": "220",
        "WDGust": "48",
        "PrecpHour": "...",
        "StnPresMin": "898.3",
        "RHMin": "98",
        "StnPresMinTime": "2018-12-30 14:11",
        "WGustTime": "2018-12-30 20:06",
        "WS": "3.9",
        "StnPresMax": "903.6",
        "VisbMean": "...",
        "SunShine": "...",
        "PrecpMax10": "...",
        "PrecpMax10Time": "",
        "EvapA": "...",
        "T Max": "9.0",
        "UVI Max Time": "",
        "PrecpHrMax": "...",
        "WSGust": "23.1",
        "PrecpHrMaxTime": "",
        "SunShineRate": "...",
        "Precp": "49.0"
    },
    "24": {
        "StnPresMaxTime": "2018-12-24 08:21",
        "StnPres": "896.5",
        "RH": "99",
        "SeaPres": "...",
        "T Max Time": "2018-12-24 23:32",
        "UVI Max": "...",
        "Td dew point": "...",
        "T Min": "8.2",
        "Temperature": "10.5",
        "T Min Time": "2018-12-24 04:29",
        "GloblRad": "...",
        "ObsTime": "24",
        "Cloud Amount": "...",
        "RHMinTime": "2018-12-24 23:42",
        "WD": "72",
        "WDGust": "64",
        "PrecpHour": "...",
        "StnPresMin": "894.1",
        "RHMin": "98",
        "StnPresMinTime": "2018-12-24 23:02",
        "WGustTime": "2018-12-24 01:00",
        "WS": "4.2",
        "StnPresMax": "899.1",
        "VisbMean": "...",
        "SunShine": "...",
        "PrecpMax10": "...",
        "PrecpMax10Time": "",
        "EvapA": "...",
        "T Max": "12.3",
        "UVI Max Time": "",
        "PrecpHrMax": "...",
        "WSGust": "21.5",
        "PrecpHrMaxTime": "",
        "SunShineRate": "...",
        "Precp": "41.0"
    }
}